requers-0.1.1.dist-info/METADATA
requers-0.1.1.dist-info/WHEEL
requers/__init__.py
requers/__init__.pyi
requers/__pycache__/__init__.cpython-313.pyc
requers/py.typed
requers/requers.cpython-312-darwin.so
requers-0.1.1.dist-info/RECORD
