Metadata-Version: 2.4
Name: requers
Version: 0.1.1
Classifier: Development Status :: 3 - Alpha
Classifier: License :: OSI Approved :: MIT License
Classifier: Programming Language :: Rust
Classifier: Programming Language :: Python :: Implementation :: CPython
Classifier: Programming Language :: Python :: 3
Classifier: Programming Language :: Python :: 3.12
Classifier: Programming Language :: Python :: 3.13
Classifier: Operating System :: OS Independent
Classifier: Topic :: Internet :: WWW/HTTP
Classifier: Typing :: Typed
Summary: A Rust-based HTTP client for Python with some requests-like methods.
Keywords: http,client,requests,rust,python
Author-email: M Zidane <92719420+moooozi@users.noreply.github.com>
License-Expression: MIT
Requires-Python: >=3.12
Project-URL: repository, https://github.com/moooozi/requers
